[{"__type__":"cc.SpriteFrame","content":{"name":"face11","texture":"2d160ef9-d5f8-459d-827e-46a4ff68fd4a","rect":[0,0,116,112],"offset":[0,0],"originalSize":[116,112]}},{"__type__":"cc.SpriteFrame","content":{"name":"face6","texture":"506886fa-f470-4154-8709-e58d0743b698","rect":[0,0,108,112],"offset":[0,0],"originalSize":[108,112]}},{"__type__":"cc.SpriteFrame","content":{"name":"face7","texture":"1a9c9796-9e32-408f-bdf4-54b20a2b8690","rect":[0,0,110,112],"offset":[0,0],"originalSize":[110,112]}},{"__type__":"cc.SpriteFrame","content":{"name":"face3","texture":"640585e5-a179-4413-af14-9c13914c3209","rect":[0,0,132,112],"offset":[0,0],"originalSize":[132,112]}},{"__type__":"cc.SpriteFrame","content":{"name":"face12","texture":"87e2a9f4-f5b5-4e23-877e-baf61e9a5bea","rect":[0,0,116,114],"offset":[0,0],"originalSize":[116,114]}},{"__type__":"cc.SpriteFrame","content":{"name":"face8","texture":"674e10f2-aec5-4679-bf4b-ad9555dec3d3","rect":[0,0,111,112],"offset":[0,0],"originalSize":[111,112]}},{"__type__":"cc.SpriteFrame","content":{"name":"face5","texture":"6ac8527a-5808-44f9-a40a-7b614c1471ea","rect":[0,0,106,112],"offset":[0,0],"originalSize":[106,112]}},{"__type__":"cc.SpriteFrame","content":{"name":"face2","texture":"462136aa-215c-4c5b-86a3-ed69b1698f2d","rect":[0,0,106,112],"offset":[0,0],"originalSize":[106,112]}},{"__type__":"cc.SpriteFrame","content":{"name":"face4","texture":"f3e22a6f-9fde-47e7-b72b-74125d42b90b","rect":[0,0,160,112],"offset":[0,0],"originalSize":[160,112]}},{"__type__":"cc.SpriteFrame","content":{"name":"face9","texture":"4742f742-00b2-44e8-aeb6-3abb9854d9c2","rect":[0,0,108,112],"offset":[0,0],"originalSize":[108,112]}},{"__type__":"cc.SpriteFrame","content":{"name":"face1","texture":"f0575d87-8082-45ae-8556-356b44b8b0f1","rect":[0,0,108,112],"offset":[0,0],"originalSize":[108,112]}},{"__type__":"cc.SpriteFrame","content":{"name":"face10","texture":"0bedf538-6399-4041-8670-2a8aeae71cbc","rect":[0,0,122,114],"offset":[0,0],"originalSize":[122,114]}},[{"__type__":"cc.Prefab","_name":"Bullfight_ExpressionView","data":{"__id__":1}},{"__type__":"cc.Node","_name":"Bullfight_ExpressionView","_contentSize":{"__type__":"cc.Size","width":1080,"height":1920},"_children":[{"__id__":2},{"__id__":3}],"_position":{"__type__":"cc.Vec2","x":540,"y":960},"_components":[{"__type__":"5c028k2O/hM4ZGfODgoVJzd","node":{"__id__":1}}],"_prefab":{"__type__":"cc.PrefabInfo","root":{"__id__":1},"fileId":"fc8b8FaLhdHUrPNmML135wO"}},{"__type__":"cc.Node","_name":"Graylayer","_opacity":180,"_color":{"__type__":"cc.Color"},"_parent":{"__id__":1},"_contentSize":{"__type__":"cc.Size","width":1080,"height":1920},"_components":[{"__type__":"cc.Sprite","node":{"__id__":2},"_spriteFrame":{"__uuid__":"a23235d1-15db-4b95-8439-a2e005bfff91"},"_sizeMode":0}],"_prefab":{"__type__":"cc.PrefabInfo","root":{"__id__":1},"fileId":"1049c9wzrxM/J/677K0dKuO"}},{"__type__":"cc.Node","_name":"ExpressionBg","_parent":{"__id__":1},"_contentSize":{"__type__":"cc.Size","width":1080,"height":317},"_children":[{"__id__":4},{"__id__":5},{"__id__":6},{"__id__":7},{"__id__":8},{"__id__":9},{"__id__":10},{"__id__":11},{"__id__":12},{"__id__":13},{"__id__":14},{"__id__":15}],"_position":{"__type__":"cc.Vec2","y":-801},"_components":[{"__type__":"cc.Sprite","node":{"__id__":3},"_spriteFrame":{"__uuid__":"e1fb3fd7-c8a8-4140-b784-758022e17c04"}}],"_prefab":{"__type__":"cc.PrefabInfo","root":{"__id__":1},"fileId":"f5871YB0qhL1ZPssnqCw8b0"}},{"__type__":"cc.Node","_name":"Btn12","_parent":{"__id__":3},"_contentSize":{"__type__":"cc.Size","width":122,"height":114},"_position":{"__type__":"cc.Vec2","x":88,"y":-78},"_components":[{"__type__":"cc.Sprite","node":{"__id__":4},"_spriteFrame":{"__uuid__":"cbeff606-1f96-4a29-b93e-a0a7ae0d3916"},"_sizeMode":2},{"__type__":"cc.Button","node":{"__id__":4},"transition":3,"pressedColor":{"__type__":"cc.Color","r":255,"g":255,"b":255},"pressedSprite":{"__uuid__":"e9ec654c-97a2-4787-9325-e6a10375219a"},"hoverSprite":{"__uuid__":"e9ec654c-97a2-4787-9325-e6a10375219a"},"clickEvents":[{"__type__":"cc.ClickEvent","target":{"__id__":1},"component":"Bullfight_ExpressionView","handler":"callBackBtn","customEventData":"10"}],"_N$normalColor":{"__type__":"cc.Color","r":255,"g":255,"b":255},"_N$disabledColor":{"__type__":"cc.Color","r":255,"g":255,"b":255},"_N$normalSprite":{"__uuid__":"c83912f7-2be0-4eb1-a32c-e5d527ed5ffe"},"_N$disabledSprite":{"__uuid__":"29158224-f8dd-4661-a796-1ffab537140e"},"_N$target":{"__id__":4}}],"_prefab":{"__type__":"cc.PrefabInfo","root":{"__id__":1},"fileId":"5fd6c9TkDRDn4XZ46yC/40s"}},{"__type__":"cc.Node","_name":"Btn11","_parent":{"__id__":3},"_contentSize":{"__type__":"cc.Size","width":116,"height":112},"_position":{"__type__":"cc.Vec2","x":268,"y":-78},"_components":[{"__type__":"cc.Sprite","node":{"__id__":5},"_spriteFrame":{"__uuid__":"044da9e7-0130-4164-9566-63c81aba0a66"},"_sizeMode":2},{"__type__":"cc.Button","node":{"__id__":5},"transition":3,"pressedColor":{"__type__":"cc.Color","r":255,"g":255,"b":255},"pressedSprite":{"__uuid__":"e9ec654c-97a2-4787-9325-e6a10375219a"},"hoverSprite":{"__uuid__":"e9ec654c-97a2-4787-9325-e6a10375219a"},"clickEvents":[{"__type__":"cc.ClickEvent","target":{"__id__":1},"component":"Bullfight_ExpressionView","handler":"callBackBtn","customEventData":"11"}],"_N$normalColor":{"__type__":"cc.Color","r":255,"g":255,"b":255},"_N$disabledColor":{"__type__":"cc.Color","r":255,"g":255,"b":255},"_N$normalSprite":{"__uuid__":"c83912f7-2be0-4eb1-a32c-e5d527ed5ffe"},"_N$disabledSprite":{"__uuid__":"29158224-f8dd-4661-a796-1ffab537140e"},"_N$target":{"__id__":5}}],"_prefab":{"__type__":"cc.PrefabInfo","root":{"__id__":1},"fileId":"9511emRpv5NS7TNEwdeR03q"}},{"__type__":"cc.Node","_name":"Btn1","_parent":{"__id__":3},"_contentSize":{"__type__":"cc.Size","width":108,"height":112},"_position":{"__type__":"cc.Vec2","x":-91,"y":-78},"_components":[{"__type__":"cc.Sprite","node":{"__id__":6},"_spriteFrame":{"__uuid__":"a3de08a0-b35b-4d48-9624-c6fd8b9ecc1a"},"_sizeMode":2},{"__type__":"cc.Button","node":{"__id__":6},"transition":3,"pressedColor":{"__type__":"cc.Color","r":255,"g":255,"b":255},"pressedSprite":{"__uuid__":"e9ec654c-97a2-4787-9325-e6a10375219a"},"hoverSprite":{"__uuid__":"e9ec654c-97a2-4787-9325-e6a10375219a"},"clickEvents":[{"__type__":"cc.ClickEvent","target":{"__id__":1},"component":"Bullfight_ExpressionView","handler":"callBackBtn","customEventData":"1"}],"_N$normalColor":{"__type__":"cc.Color","r":255,"g":255,"b":255},"_N$disabledColor":{"__type__":"cc.Color","r":255,"g":255,"b":255},"_N$normalSprite":{"__uuid__":"c83912f7-2be0-4eb1-a32c-e5d527ed5ffe"},"_N$disabledSprite":{"__uuid__":"29158224-f8dd-4661-a796-1ffab537140e"},"_N$target":{"__id__":6}}],"_prefab":{"__type__":"cc.PrefabInfo","root":{"__id__":1},"fileId":"02ab3V+oN5KgZ6shdcQLO70"}},{"__type__":"cc.Node","_name":"Btn2","_parent":{"__id__":3},"_contentSize":{"__type__":"cc.Size","width":116,"height":114},"_position":{"__type__":"cc.Vec2","x":447,"y":-78},"_components":[{"__type__":"cc.Sprite","node":{"__id__":7},"_spriteFrame":{"__uuid__":"538d916f-c1a6-4cd6-8e5c-3ae9d10abdc2"},"_sizeMode":2},{"__type__":"cc.Button","node":{"__id__":7},"transition":3,"pressedColor":{"__type__":"cc.Color","r":255,"g":255,"b":255},"pressedSprite":{"__uuid__":"e9ec654c-97a2-4787-9325-e6a10375219a"},"hoverSprite":{"__uuid__":"e9ec654c-97a2-4787-9325-e6a10375219a"},"clickEvents":[{"__type__":"cc.ClickEvent","target":{"__id__":1},"component":"Bullfight_ExpressionView","handler":"callBackBtn","customEventData":"2"}],"_N$normalColor":{"__type__":"cc.Color","r":255,"g":255,"b":255},"_N$disabledColor":{"__type__":"cc.Color","r":255,"g":255,"b":255},"_N$normalSprite":{"__uuid__":"c83912f7-2be0-4eb1-a32c-e5d527ed5ffe"},"_N$disabledSprite":{"__uuid__":"29158224-f8dd-4661-a796-1ffab537140e"},"_N$target":{"__id__":7}}],"_prefab":{"__type__":"cc.PrefabInfo","root":{"__id__":1},"fileId":"44a0c4YaIRFEIRTYKE2Ez5/"}},{"__type__":"cc.Node","_name":"Btn3","_parent":{"__id__":3},"_contentSize":{"__type__":"cc.Size","width":111,"height":112},"_position":{"__type__":"cc.Vec2","x":-271,"y":-78},"_components":[{"__type__":"cc.Sprite","node":{"__id__":8},"_spriteFrame":{"__uuid__":"6e59d5f7-5a00-4b4f-abbe-48908f8f1d31"},"_sizeMode":2},{"__type__":"cc.Button","node":{"__id__":8},"transition":3,"pressedColor":{"__type__":"cc.Color","r":255,"g":255,"b":255},"pressedSprite":{"__uuid__":"e9ec654c-97a2-4787-9325-e6a10375219a"},"hoverSprite":{"__uuid__":"e9ec654c-97a2-4787-9325-e6a10375219a"},"clickEvents":[{"__type__":"cc.ClickEvent","target":{"__id__":1},"component":"Bullfight_ExpressionView","handler":"callBackBtn","customEventData":"3"}],"_N$normalColor":{"__type__":"cc.Color","r":255,"g":255,"b":255},"_N$disabledColor":{"__type__":"cc.Color","r":255,"g":255,"b":255},"_N$normalSprite":{"__uuid__":"c83912f7-2be0-4eb1-a32c-e5d527ed5ffe"},"_N$disabledSprite":{"__uuid__":"29158224-f8dd-4661-a796-1ffab537140e"},"_N$target":{"__id__":8}}],"_prefab":{"__type__":"cc.PrefabInfo","root":{"__id__":1},"fileId":"0fe9fue4DNCRIA4hBlWLDad"}},{"__type__":"cc.Node","_name":"Btn4","_parent":{"__id__":3},"_contentSize":{"__type__":"cc.Size","width":110,"height":112},"_position":{"__type__":"cc.Vec2","x":-450,"y":-78},"_components":[{"__type__":"cc.Sprite","node":{"__id__":9},"_spriteFrame":{"__uuid__":"42b02404-e60a-45c6-834d-52e6e2858f3c"},"_sizeMode":2},{"__type__":"cc.Button","node":{"__id__":9},"transition":3,"pressedColor":{"__type__":"cc.Color","r":255,"g":255,"b":255},"pressedSprite":{"__uuid__":"e9ec654c-97a2-4787-9325-e6a10375219a"},"hoverSprite":{"__uuid__":"e9ec654c-97a2-4787-9325-e6a10375219a"},"clickEvents":[{"__type__":"cc.ClickEvent","target":{"__id__":1},"component":"Bullfight_ExpressionView","handler":"callBackBtn","customEventData":"4"}],"_N$normalColor":{"__type__":"cc.Color","r":255,"g":255,"b":255},"_N$disabledColor":{"__type__":"cc.Color","r":255,"g":255,"b":255},"_N$normalSprite":{"__uuid__":"c83912f7-2be0-4eb1-a32c-e5d527ed5ffe"},"_N$disabledSprite":{"__uuid__":"29158224-f8dd-4661-a796-1ffab537140e"},"_N$target":{"__id__":9}}],"_prefab":{"__type__":"cc.PrefabInfo","root":{"__id__":1},"fileId":"ca9a4QVLPRPnZG1bg1b+rDA"}},{"__type__":"cc.Node","_name":"Btn5","_parent":{"__id__":3},"_contentSize":{"__type__":"cc.Size","width":108,"height":112},"_position":{"__type__":"cc.Vec2","x":444,"y":72},"_components":[{"__type__":"cc.Sprite","node":{"__id__":10},"_spriteFrame":{"__uuid__":"42077d6a-6725-4bbf-b230-93526bcae02d"},"_sizeMode":2},{"__type__":"cc.Button","node":{"__id__":10},"transition":3,"pressedColor":{"__type__":"cc.Color","r":255,"g":255,"b":255},"pressedSprite":{"__uuid__":"e9ec654c-97a2-4787-9325-e6a10375219a"},"hoverSprite":{"__uuid__":"e9ec654c-97a2-4787-9325-e6a10375219a"},"clickEvents":[{"__type__":"cc.ClickEvent","target":{"__id__":1},"component":"Bullfight_ExpressionView","handler":"callBackBtn","customEventData":"5"}],"_N$normalColor":{"__type__":"cc.Color","r":255,"g":255,"b":255},"_N$disabledColor":{"__type__":"cc.Color","r":255,"g":255,"b":255},"_N$normalSprite":{"__uuid__":"c83912f7-2be0-4eb1-a32c-e5d527ed5ffe"},"_N$disabledSprite":{"__uuid__":"29158224-f8dd-4661-a796-1ffab537140e"},"_N$target":{"__id__":10}}],"_prefab":{"__type__":"cc.PrefabInfo","root":{"__id__":1},"fileId":"58249kDyKROP5c/niB2IX8B"}},{"__type__":"cc.Node","_name":"Btn6","_parent":{"__id__":3},"_contentSize":{"__type__":"cc.Size","width":106,"height":112},"_position":{"__type__":"cc.Vec2","x":265,"y":72},"_components":[{"__type__":"cc.Sprite","node":{"__id__":11},"_spriteFrame":{"__uuid__":"756db5cb-b413-4e63-a2bd-ea706f85505c"},"_sizeMode":2},{"__type__":"cc.Button","node":{"__id__":11},"transition":3,"pressedColor":{"__type__":"cc.Color","r":255,"g":255,"b":255},"pressedSprite":{"__uuid__":"e9ec654c-97a2-4787-9325-e6a10375219a"},"hoverSprite":{"__uuid__":"e9ec654c-97a2-4787-9325-e6a10375219a"},"clickEvents":[{"__type__":"cc.ClickEvent","target":{"__id__":1},"component":"Bullfight_ExpressionView","handler":"callBackBtn","customEventData":"6"}],"_N$normalColor":{"__type__":"cc.Color","r":255,"g":255,"b":255},"_N$disabledColor":{"__type__":"cc.Color","r":255,"g":255,"b":255},"_N$normalSprite":{"__uuid__":"c83912f7-2be0-4eb1-a32c-e5d527ed5ffe"},"_N$disabledSprite":{"__uuid__":"29158224-f8dd-4661-a796-1ffab537140e"},"_N$target":{"__id__":11}}],"_prefab":{"__type__":"cc.PrefabInfo","root":{"__id__":1},"fileId":"a41afEAU89D2LKxwa751vmq"}},{"__type__":"cc.Node","_name":"Btn7","_parent":{"__id__":3},"_contentSize":{"__type__":"cc.Size","width":160,"height":112},"_position":{"__type__":"cc.Vec2","x":86,"y":72},"_components":[{"__type__":"cc.Sprite","node":{"__id__":12},"_spriteFrame":{"__uuid__":"9f7291ac-2605-4503-8002-7fb39183c2eb"},"_sizeMode":2},{"__type__":"cc.Button","node":{"__id__":12},"transition":3,"pressedColor":{"__type__":"cc.Color","r":255,"g":255,"b":255},"pressedSprite":{"__uuid__":"e9ec654c-97a2-4787-9325-e6a10375219a"},"hoverSprite":{"__uuid__":"e9ec654c-97a2-4787-9325-e6a10375219a"},"clickEvents":[{"__type__":"cc.ClickEvent","target":{"__id__":1},"component":"Bullfight_ExpressionView","handler":"callBackBtn","customEventData":"7"}],"_N$normalColor":{"__type__":"cc.Color","r":255,"g":255,"b":255},"_N$disabledColor":{"__type__":"cc.Color","r":255,"g":255,"b":255},"_N$normalSprite":{"__uuid__":"c83912f7-2be0-4eb1-a32c-e5d527ed5ffe"},"_N$disabledSprite":{"__uuid__":"29158224-f8dd-4661-a796-1ffab537140e"},"_N$target":{"__id__":12}}],"_prefab":{"__type__":"cc.PrefabInfo","root":{"__id__":1},"fileId":"161d9kVCtpOYaiheRx4bspU"}},{"__type__":"cc.Node","_name":"Btn8","_parent":{"__id__":3},"_contentSize":{"__type__":"cc.Size","width":132,"height":112},"_position":{"__type__":"cc.Vec2","x":-92,"y":72},"_components":[{"__type__":"cc.Sprite","node":{"__id__":13},"_spriteFrame":{"__uuid__":"4cf5d1de-c874-467f-bd45-4ff6e69f9471"},"_sizeMode":2},{"__type__":"cc.Button","node":{"__id__":13},"transition":3,"pressedColor":{"__type__":"cc.Color","r":255,"g":255,"b":255},"pressedSprite":{"__uuid__":"e9ec654c-97a2-4787-9325-e6a10375219a"},"hoverSprite":{"__uuid__":"e9ec654c-97a2-4787-9325-e6a10375219a"},"clickEvents":[{"__type__":"cc.ClickEvent","target":{"__id__":1},"component":"Bullfight_ExpressionView","handler":"callBackBtn","customEventData":"8"}],"_N$normalColor":{"__type__":"cc.Color","r":255,"g":255,"b":255},"_N$disabledColor":{"__type__":"cc.Color","r":255,"g":255,"b":255},"_N$normalSprite":{"__uuid__":"c83912f7-2be0-4eb1-a32c-e5d527ed5ffe"},"_N$disabledSprite":{"__uuid__":"29158224-f8dd-4661-a796-1ffab537140e"},"_N$target":{"__id__":13}}],"_prefab":{"__type__":"cc.PrefabInfo","root":{"__id__":1},"fileId":"da683JGjuBASJAER2E3rtkg"}},{"__type__":"cc.Node","_name":"Btn9","_parent":{"__id__":3},"_contentSize":{"__type__":"cc.Size","width":106,"height":112},"_position":{"__type__":"cc.Vec2","x":-271,"y":72},"_components":[{"__type__":"cc.Sprite","node":{"__id__":14},"_spriteFrame":{"__uuid__":"79621b63-d895-46af-9c1b-e88b99152931"},"_sizeMode":2},{"__type__":"cc.Button","node":{"__id__":14},"transition":3,"pressedColor":{"__type__":"cc.Color","r":255,"g":255,"b":255},"pressedSprite":{"__uuid__":"e9ec654c-97a2-4787-9325-e6a10375219a"},"hoverSprite":{"__uuid__":"e9ec654c-97a2-4787-9325-e6a10375219a"},"clickEvents":[{"__type__":"cc.ClickEvent","target":{"__id__":1},"component":"Bullfight_ExpressionView","handler":"callBackBtn","customEventData":"9"}],"_N$normalColor":{"__type__":"cc.Color","r":255,"g":255,"b":255},"_N$disabledColor":{"__type__":"cc.Color","r":255,"g":255,"b":255},"_N$normalSprite":{"__uuid__":"c83912f7-2be0-4eb1-a32c-e5d527ed5ffe"},"_N$disabledSprite":{"__uuid__":"29158224-f8dd-4661-a796-1ffab537140e"},"_N$target":{"__id__":14}}],"_prefab":{"__type__":"cc.PrefabInfo","root":{"__id__":1},"fileId":"1e24fdGrLNPOI9qsjssNhy+"}},{"__type__":"cc.Node","_name":"Btn10","_parent":{"__id__":3},"_contentSize":{"__type__":"cc.Size","width":108,"height":112},"_position":{"__type__":"cc.Vec2","x":-450,"y":72},"_components":[{"__type__":"cc.Sprite","node":{"__id__":15},"_spriteFrame":{"__uuid__":"c83912f7-2be0-4eb1-a32c-e5d527ed5ffe"},"_sizeMode":2},{"__type__":"cc.Button","node":{"__id__":15},"transition":3,"pressedColor":{"__type__":"cc.Color","r":255,"g":255,"b":255},"pressedSprite":{"__uuid__":"e9ec654c-97a2-4787-9325-e6a10375219a"},"hoverSprite":{"__uuid__":"e9ec654c-97a2-4787-9325-e6a10375219a"},"clickEvents":[{"__type__":"cc.ClickEvent","target":{"__id__":1},"component":"Bullfight_ExpressionView","handler":"callBackBtn","customEventData":"10"}],"_N$normalColor":{"__type__":"cc.Color","r":255,"g":255,"b":255},"_N$disabledColor":{"__type__":"cc.Color","r":255,"g":255,"b":255},"_N$normalSprite":{"__uuid__":"c83912f7-2be0-4eb1-a32c-e5d527ed5ffe"},"_N$disabledSprite":{"__uuid__":"29158224-f8dd-4661-a796-1ffab537140e"},"_N$target":{"__id__":15}}],"_prefab":{"__type__":"cc.PrefabInfo","root":{"__id__":1},"fileId":"959b1TZee5Hb4wY0rUTXFAW"}}],{"__type__":"cc.SpriteFrame","content":{"name":"ExpressionBg","texture":"848cf1be-4d3c-4894-aae3-c8ea3bd0deec","rect":[0,0,1080,317],"offset":[0,0],"originalSize":[1080,317]}}]